{"examples":[{"translation":"我们将不得不冒着可能遇上敌人巡逻兵的危险。","first":"We'll have to risk meeting an enemy ","last":"."},{"translation":"巡逻队遭到土匪伏击.","first":"The ","last":" was waylaid by bandits."},{"translation":"他们埋伏起来准备伏击巡逻的敌人。","first":"They laid an ambush for the enemy ","last":"."}],"pronunciation":{"uk":{"phonetic":"pə'trəʊl","audio":"patrol-uk.mp3"},"us":{"phonetic":"pə'troʊl","audio":"patrol-us.mp3"}},"definition":{"en":{"v":["maintain the security of by carrying out a patrol"],"n":["a detachment used for security or reconnaissance","the activity of going around or through an area at regular intervals for security purposes","a group that goes through a region at regular intervals for the purpose of security"]},"cn":{"vt.&vi":["巡逻,巡查"],"n":["巡逻,巡查"]}},"id":7880,"content":"patrol"}