{"examples":[{"translation":"一组护士协助医生施行手术。","first":"A team of nurses ","last":" the doctor in performing the operation."},{"translation":"他请求我们帮他完成他的计划。","first":"He asked us to ","last":" him in carrying through his plan."},{"translation":"帮助记忆的有关，帮助，或试图帮助记忆的","first":"Relating to, assisting, or intended to ","last":" the memory."}],"pronunciation":{"uk":{"phonetic":"ə'sɪst","audio":"assist-uk.mp3"},"us":{"phonetic":"ə'sɪst","audio":"assist-us.mp3"}},"definition":{"en":{"v":["give help or assistance; be of service","act as an assistant in a subordinate or supportive function","work for or be a servant to"],"n":["the activity of contributing to the fulfillment of a need or furtherance of an effort or purpose","(sports) the act of enabling another player to make a good play"]},"cn":{"vi":["帮助,协助,出席"],"n":["帮助,协助,协助的器械"],"vt":["帮助,协助"]}},"id":984,"content":"assist"}