{"examples":[{"translation":"货物已装箱待运。","first":"The goods have been cased up for ","last":"."},{"translation":"伦敦运输公司会在交通高峰时间增开班车。","first":"London ","last":" run extra trains during the rush-hour."},{"translation":"请另外找一个运输方法。","first":"Please find alternative means of ","last":"."}],"pronunciation":{"uk":{"phonetic":"'trænspɔːt","audio":"transport-uk.mp3"},"us":{"phonetic":"'trænspɔːrt","audio":"transport-us.mp3"}},"definition":{"en":{"v":["move something or somebody around; usually over long distances","move while supporting, either in a vehicle or in one's hands or on one's body","hold spellbound"],"n":["something that serves as a means of transportation","an exchange of molecules (and their kinetic energy and momentum) across the boundary between adjacent layers of a fluid or across cell membranes","the commercial enterprise of moving goods and materials"]},"cn":{"vt":["运输；流放；为强烈的情绪所激动"],"n":["运输、运输工具；(常用复数）强烈的情绪、狂喜或狂怒"]}},"id":6229,"content":"transport"}