{"examples":[{"translation":"警察逮捕了好几个人。","first":"The police made several ","last":"."},{"translation":"警察逮捕了小偷。","first":"The police ","last":" the thief."},{"translation":"暴乱导致3 个年轻人被捕。","first":"The riot led to the ","last":" of three young men."}],"pronunciation":{"uk":{"phonetic":"ə'rest","audio":"arrest-uk.mp3"},"us":{"phonetic":"ə'rest","audio":"arrest-us.mp3"}},"definition":{"en":{"v":["take into custody","hold back, as of a danger or an enemy; check the expansion or influence of","attract and fix"],"n":["the act of apprehending (especially apprehending a criminal)","the state of inactivity following an interruption"]},"cn":{"n":["逮捕,监禁"],"vt":["拘捕,妨碍,吸引"]}},"id":941,"content":"arrest"}