{"examples":[{"translation":"她的头部与身体大小不成比例。","first":"Her head is out of ","last":" to the size of her body."},{"translation":"我们正努力把问题缩小到可以控制的范围内。","first":"We are trying to reduce the problem to manageable ","last":"."},{"translation":"这幅画比例失调。","first":"This painting lacks ","last":"."}],"pronunciation":{"uk":{"phonetic":"prə'pɔːʃn","audio":"proportion-uk.mp3"},"us":{"phonetic":"prə'pɔːrʃn","audio":"proportion-us.mp3"}},"definition":{"en":{"v":["give pleasant proportions to","adjust in size relative to other things"],"n":["the quotient obtained when the magnitude of a part is divided by the magnitude of the whole","magnitude or extent","balance among the parts of something"]},"cn":{"n":["比例,均衡,部份"],"vt":["使成比例,使均衡,分摊"]}},"id":4839,"content":"proportion"}