{"examples":[{"translation":"这次罢工造成停产一周。","first":"The strike ","last":" up production for a week."},{"translation":"这腰带是在前面打结还是在後面？","first":"Does this sash ","last":" in front or at the back?"},{"translation":"几个星期来她一直呆在家中照顾有病的父亲。","first":"She has been ","last":" to the house for weeks looking after her invalid father."}],"pronunciation":{"uk":{"phonetic":"taɪ","audio":"tie-uk.mp3"},"us":{"phonetic":"taɪ","audio":"tie-us.mp3"}},"definition":{"en":{"v":["fasten or secure with a rope, string, or cord","finish a game with an equal number of points, goals, etc.","limit or restrict to"],"n":["neckwear consisting of a long narrow piece of material worn (mostly by men) under a collar and tied in knot at the front","a social or business relationship","equality of score in a contest"]},"cn":{"vi":["打结,连结"],"n":["结,束缚,不分胜负,(领)带"],"vt":["系,约束,捆绑"]}},"id":6137,"content":"tie"}