{"examples":[{"translation":"你有资格领取失业救济金吗？","first":"Are you entitled to unemployment ","last":"?"},{"translation":"这项工程对每个人都大有好处。","first":"This project is of great ","last":" to everyone."},{"translation":"广泛的阅读使我受益匪浅。","first":"I have ","last":" a lot from extensive reading."}],"pronunciation":{"uk":{"phonetic":"'benɪfɪt","audio":"benefit-uk.mp3"},"us":{"phonetic":"'benɪfɪt","audio":"benefit-us.mp3"}},"definition":{"en":{"v":["derive a benefit from","be beneficial for"],"n":["financial assistance in time of need","something that aids or promotes well-being","a performance to raise money for a charitable cause"]},"cn":{"vi":["得益"],"n":["利益, 津贴; 义卖, 义演"],"vt":["有益于"]}},"id":1209,"content":"benefit"}